fcmtool_bqmn/__init__.py
fcmtool_bqmn/fcmtool_bqmn.py
fcmtool_bqmn-0.0.1.3.dist-info/METADATA
fcmtool_bqmn-0.0.1.3.dist-info/WHEEL
fcmtool_bqmn-0.0.1.3.dist-info/top_level.txt
fcmtool_bqmn-0.0.1.3.dist-info/RECORD
