Metadata-Version: 2.2
Name: fcmtool_bqmn
Version: 0.0.1.3
Summary: My first Python package for extracting Functional Connectivity Matrices
Author: Quoc Minh Nhat Bui
Author-email: star.buiquocminhnhat.0510@gmail.com
Keywords: python,first package
Classifier: Development Status :: 3 - Alpha
Classifier: Intended Audience :: Education
Classifier: Programming Language :: Python :: 2
Classifier: Programming Language :: Python :: 3
Classifier: Operating System :: MacOS :: MacOS X
Classifier: Operating System :: Microsoft :: Windows
Requires-Dist: numpy
Requires-Dist: glob2
Requires-Dist: pathlib
Requires-Dist: nilearn
Requires-Dist: load_confounds
Dynamic: author
Dynamic: author-email
Dynamic: classifier
Dynamic: description
Dynamic: keywords
Dynamic: requires-dist
Dynamic: summary
